qrcite.py
qrcite-0.3.1.dist-info/entry_points.txt
qrcite-0.3.1.dist-info/WHEEL
qrcite-0.3.1.dist-info/METADATA
qrcite-0.3.1.dist-info/RECORD
