Metadata-Version: 2.1
Name: qrcite
Version: 0.3.1
Summary: Small python tool to generate qr codes with doi links out of .bib files. 
Author-email: Mathias <mathias-handy@gmx.de>, "Erik E. Lorenz" <erik@tuvero.de>
Requires-Python: >=3.9
Requires-Dist: bibtexparser
Requires-Dist: qrcode>=7.4
Requires-Dist: Pillow
Requires-Dist: fonts
Requires-Dist: font-fredoka-one
Requires-Dist: habanero
Requires-Dist: pandas
Project-URL: Homepage, https://codeberg.org/Meph/qrcite/
